keprompt/AiAnthropic.py
keprompt/AiDeepSeek.py
keprompt/AiGoogle.py
keprompt/AiMistral.py
keprompt/AiOpenAi.py
keprompt/AiOpenRouter.py
keprompt/AiPrompt.py
keprompt/AiProvider.py
keprompt/AiXai.py
keprompt/CustomEncoder.py
keprompt/ModelManager.py
keprompt/Prompt.py
keprompt/__init__.py
keprompt/__main__.py
keprompt/api.py
keprompt/chat_manager.py
keprompt/chat_viewer.py
keprompt/config.py
keprompt/cost_cli.py
keprompt/cost_tracker.py
keprompt/database.py
keprompt/db_cli.py
keprompt/function_loader.py
keprompt/http_server.py
keprompt/keprompt.py
keprompt/keprompt_builtins.py
keprompt/keprompt_functions.py
keprompt/keprompt_logger.py
keprompt/keprompt_util.py
keprompt/keprompt_utils.py
keprompt/keprompt_vm.py
keprompt/model_updater.py
keprompt/process_utils.py
keprompt/server_registry.py
keprompt/version.py
keprompt/web_gui/README.md
keprompt/web_gui/app.js
keprompt/web_gui/favicon.svg
keprompt/web_gui/index.html
keprompt/web_gui/styles.css
keprompt-2.0.4.dist-info/licenses/LICENSE
keprompt-2.0.4.dist-info/METADATA
keprompt-2.0.4.dist-info/WHEEL
keprompt-2.0.4.dist-info/entry_points.txt
keprompt-2.0.4.dist-info/top_level.txt
keprompt-2.0.4.dist-info/RECORD
