Metadata-Version: 2.4
Name: keprompt
Version: 2.0.4
Summary: A prompt engineering tool for large language models
Author-email: Jerry Westrick <jerry@westrick.com>
Requires-Python: >=3.8
License-File: LICENSE
Requires-Dist: keyring>=24.0.0
Requires-Dist: rich>=13.0.0
Requires-Dist: requests>=2.31.0
Provides-Extra: dev
Requires-Dist: pytest>=7.0.0; extra == "dev"
Requires-Dist: black>=23.0.0; extra == "dev"
Requires-Dist: isort>=5.12.0; extra == "dev"
Dynamic: license-file
